sigmatmpy/API.py
sigmatmpy/APIadmin.py
sigmatmpy/__init__.py
sigmatmpy/error.py
sigmatmpy/information.py
sigmatmpy/manager_config.py
sigmatmpy-0.0.27.dist-info/LICENSE
sigmatmpy-0.0.27.dist-info/METADATA
sigmatmpy-0.0.27.dist-info/WHEEL
sigmatmpy-0.0.27.dist-info/top_level.txt
sigmatmpy-0.0.27.dist-info/RECORD
