Metadata-Version: 2.1
Name: sigmatmpy
Version: 0.0.27
Summary: SigmaTM manager api for python user
Home-page: UNKNOWN
Author: SigmaTM
Author-email: wuyou1020@hotmail.com
License: UNKNOWN
Platform: UNKNOWN
Classifier: Programming Language :: Python :: 3
Classifier: License :: OSI Approved :: MIT License
Classifier: Operating System :: OS Independent
Requires-Dist: pandas
Requires-Dist: websocket-client
